omg/__init__.py
omg/cli.py
omg/common/__init__.py
omg/common/exceptions.py
omg/common/logger.py
omg/common/meta.py
omg/common/node.py
omg/common/path.py
omg/common/render.py
omg/common/tools.py
omg/core/__init__.py
omg/core/git.py
omg/core/models.py
omg/core/repository.py
omg/core/scaffold.py
omg/core/settings.py
omg/odoo/__init__.py
omg/odoo/field.py
omg/odoo/model.py
omg/odoo/module.py
omg/odoo/odoo.py
odoo_module_generator-0.2.1.dist-info/METADATA
odoo_module_generator-0.2.1.dist-info/WHEEL
odoo_module_generator-0.2.1.dist-info/entry_points.txt
odoo_module_generator-0.2.1.dist-info/top_level.txt
odoo_module_generator-0.2.1.dist-info/RECORD
